{
  "setting": "none",
  "seed": 0,
  "config": {
    "id": "h128_lr3e4_d30_focal",
    "hidden": 128,
    "lr": 0.0003,
    "dropout": 0.3,
    "loss": "focal"
  },
  "history": [
    {
      "epoch": 1,
      "train_loss": 0.16867908022620462,
      "val_auc": 0.5606604222218449
    },
    {
      "epoch": 2,
      "train_loss": 0.14524940965753613,
      "val_auc": 0.5712669202941626
    },
    {
      "epoch": 3,
      "train_loss": 0.13303362916816364,
      "val_auc": 0.5795720885205251
    },
    {
      "epoch": 4,
      "train_loss": 0.12989968264644797,
      "val_auc": 0.5865312760067256
    },
    {
      "epoch": 5,
      "train_loss": 0.1279306917479544,
      "val_auc": 0.5862255642928719
    },
    {
      "epoch": 6,
      "train_loss": 0.1266152389121778,
      "val_auc": 0.5830495592656125
    },
    {
      "epoch": 7,
      "train_loss": 0.1248287188284325,
      "val_auc": 0.593222965743304
    },
    {
      "epoch": 8,
      "train_loss": 0.12331274806550055,
      "val_auc": 0.5958151463170231
    },
    {
      "epoch": 9,
      "train_loss": 0.12193066423589533,
      "val_auc": 0.5878390427826559
    },
    {
      "epoch": 10,
      "train_loss": 0.12071415465889555,
      "val_auc": 0.599855211535522
    },
    {
      "epoch": 11,
      "train_loss": 0.11859728508826459,
      "val_auc": 0.5977449515107254
    },
    {
      "epoch": 12,
      "train_loss": 0.11665895807020592,
      "val_auc": 0.5911084597224817
    },
    {
      "epoch": 13,
      "train_loss": 0.11563968522982164,
      "val_auc": 0.5957026274223407
    },
    {
      "epoch": 14,
      "train_loss": 0.1119946376843886,
      "val_auc": 0.5866161959272406
    },
    {
      "epoch": 15,
      "train_loss": 0.10935213191039635,
      "val_auc": 0.5881192785203554
    }
  ],
  "best_val_auc": 0.599855211535522,
  "best_epoch": 10,
  "epochs_ran": 15,
  "test_evaluated": false
}