{
  "setting": "none",
  "seed": 1,
  "config": {
    "id": "h64_lr1e3_d10_focal",
    "hidden": 64,
    "lr": 0.001,
    "dropout": 0.1,
    "loss": "focal"
  },
  "metrics": {
    "base_rate": 0.58068669527897,
    "weighted_f1": 0.6590059196164415,
    "macro_f1": 0.6407426856959632,
    "shift_f1": 0.7539164490861618,
    "noshift_f1": 0.5275689223057645,
    "shift_precision": 0.6750438340151957,
    "shift_recall": 0.8536585365853658,
    "balanced_acc": 0.6422847442394588,
    "frac_pred_shift": 0.7343347639484978,
    "degenerate": false,
    "shift_auc": 0.7195999488607522,
    "shift_pr_auc": 0.7593558371997355,
    "brier": 0.22233186029475507,
    "ece10": 0.09212220808722942
  },
  "threshold": 0.6108909845352173,
  "history": [
    {
      "epoch": 1,
      "train_loss": 0.07233765213326974,
      "val_auc": 0.6367829198650202
    },
    {
      "epoch": 2,
      "train_loss": 0.06497087532823737,
      "val_auc": 0.6629862424444692
    },
    {
      "epoch": 3,
      "train_loss": 0.06413342374743837,
      "val_auc": 0.670611302703304
    },
    {
      "epoch": 4,
      "train_loss": 0.06269881896900409,
      "val_auc": 0.6865937998294211
    },
    {
      "epoch": 5,
      "train_loss": 0.06213523853908886,
      "val_auc": 0.697672154855935
    },
    {
      "epoch": 6,
      "train_loss": 0.06096163832328536,
      "val_auc": 0.7354266325508956
    },
    {
      "epoch": 7,
      "train_loss": 0.05933383592601978,
      "val_auc": 0.7211035710312603
    },
    {
      "epoch": 8,
      "train_loss": 0.058523033491589806,
      "val_auc": 0.7659407794712054
    },
    {
      "epoch": 9,
      "train_loss": 0.05784480499498772,
      "val_auc": 0.762904661252642
    },
    {
      "epoch": 10,
      "train_loss": 0.05709883965777628,
      "val_auc": 0.7579217191382059
    },
    {
      "epoch": 11,
      "train_loss": 0.05672191907510613,
      "val_auc": 0.7416054807727963
    },
    {
      "epoch": 12,
      "train_loss": 0.05649511764446894,
      "val_auc": 0.769704639003226
    },
    {
      "epoch": 13,
      "train_loss": 0.05487733311725385,
      "val_auc": 0.7883709719286536
    },
    {
      "epoch": 14,
      "train_loss": 0.05462963517868158,
      "val_auc": 0.7993427151703933
    },
    {
      "epoch": 15,
      "train_loss": 0.05449424119609775,
      "val_auc": 0.8011690213965217
    },
    {
      "epoch": 16,
      "train_loss": 0.05415467579256405,
      "val_auc": 0.7976971854488819
    },
    {
      "epoch": 17,
      "train_loss": 0.05348141863942146,
      "val_auc": 0.8063837282604664
    },
    {
      "epoch": 18,
      "train_loss": 0.05290769198627183,
      "val_auc": 0.7918289019913227
    },
    {
      "epoch": 19,
      "train_loss": 0.05220711344119274,
      "val_auc": 0.8022675863091928
    },
    {
      "epoch": 20,
      "train_loss": 0.05190143102046215,
      "val_auc": 0.7887417955278675
    },
    {
      "epoch": 21,
      "train_loss": 0.05209243365309455,
      "val_auc": 0.8032966217970112
    },
    {
      "epoch": 22,
      "train_loss": 0.05133174450108499,
      "val_auc": 0.7973866206845404
    }
  ],
  "best_val_auc": 0.8063837282604664,
  "best_epoch": 17,
  "epochs_ran": 22,
  "scores_file": "final_none_seed1.npz"
}