{
  "setting": "oracle",
  "seed": 2,
  "config": {
    "id": "h128_lr3e4_d30_focal",
    "hidden": 128,
    "lr": 0.0003,
    "dropout": 0.3,
    "loss": "focal"
  },
  "metrics": {
    "base_rate": 0.19581845996940336,
    "weighted_f1": 0.7910082439673176,
    "macro_f1": 0.6833394786153639,
    "shift_f1": 0.5063583815028901,
    "noshift_f1": 0.8603205757278377,
    "shift_precision": 0.4553014553014553,
    "shift_recall": 0.5703125,
    "balanced_acc": 0.7020871314204185,
    "frac_pred_shift": 0.24528301886792453,
    "degenerate": false,
    "shift_auc": 0.7931169120928158,
    "shift_pr_auc": 0.5770125492524532,
    "brier": 0.1666857719234412,
    "ece10": 0.20956102510071695
  },
  "threshold": 0.5167370438575745,
  "history": [
    {
      "epoch": 1,
      "train_loss": 0.10623992722609947,
      "val_auc": 0.7542187676016672
    },
    {
      "epoch": 2,
      "train_loss": 0.09317898949415519,
      "val_auc": 0.7750536061810258
    },
    {
      "epoch": 3,
      "train_loss": 0.09001881282391219,
      "val_auc": 0.789545920686159
    },
    {
      "epoch": 4,
      "train_loss": 0.08729671969495971,
      "val_auc": 0.8026592356069346
    },
    {
      "epoch": 5,
      "train_loss": 0.08515459855740097,
      "val_auc": 0.8111941747949953
    },
    {
      "epoch": 6,
      "train_loss": 0.08303452754157713,
      "val_auc": 0.8150416807480004
    },
    {
      "epoch": 7,
      "train_loss": 0.0816725747467115,
      "val_auc": 0.8084859944140805
    },
    {
      "epoch": 8,
      "train_loss": 0.08069825073939631,
      "val_auc": 0.8173891847587529
    },
    {
      "epoch": 9,
      "train_loss": 0.0796859014950607,
      "val_auc": 0.8221949011975932
    },
    {
      "epoch": 10,
      "train_loss": 0.07834566789197511,
      "val_auc": 0.8065702532309377
    },
    {
      "epoch": 11,
      "train_loss": 0.07688878226126063,
      "val_auc": 0.8182792221665443
    },
    {
      "epoch": 12,
      "train_loss": 0.0756100274344114,
      "val_auc": 0.8224453547136537
    },
    {
      "epoch": 13,
      "train_loss": 0.07457316910912251,
      "val_auc": 0.8221089565051879
    },
    {
      "epoch": 14,
      "train_loss": 0.07358808629214764,
      "val_auc": 0.8073839600983556
    },
    {
      "epoch": 15,
      "train_loss": 0.07231670694061737,
      "val_auc": 0.8233162609300284
    },
    {
      "epoch": 16,
      "train_loss": 0.07039292162048748,
      "val_auc": 0.8204828052347599
    },
    {
      "epoch": 17,
      "train_loss": 0.06973430428696775,
      "val_auc": 0.8151553025447398
    },
    {
      "epoch": 18,
      "train_loss": 0.06785427826060646,
      "val_auc": 0.8008403157326371
    },
    {
      "epoch": 19,
      "train_loss": 0.06717025368720636,
      "val_auc": 0.7997451764148342
    },
    {
      "epoch": 20,
      "train_loss": 0.0656812202891913,
      "val_auc": 0.7965953277163379
    }
  ],
  "best_val_auc": 0.8233162609300284,
  "best_epoch": 15,
  "epochs_ran": 20,
  "scores_file": "final_oracle_seed2.npz"
}