{
  "setting": "none",
  "seed": 0,
  "config": {
    "id": "h256_lr3e4_d30_cbce",
    "hidden": 256,
    "lr": 0.0003,
    "dropout": 0.3,
    "loss": "cb_ce"
  },
  "history": [
    {
      "epoch": 1,
      "train_loss": 0.5624920385224479,
      "val_auc": 0.5573823088455772
    },
    {
      "epoch": 2,
      "train_loss": 0.5381351283618382,
      "val_auc": 0.5759250374812594
    },
    {
      "epoch": 3,
      "train_loss": 0.5217029196875436,
      "val_auc": 0.5770314842578711
    },
    {
      "epoch": 4,
      "train_loss": 0.5085755870455787,
      "val_auc": 0.580047976011994
    },
    {
      "epoch": 5,
      "train_loss": 0.49696366276059833,
      "val_auc": 0.570383808095952
    },
    {
      "epoch": 6,
      "train_loss": 0.4704200966017587,
      "val_auc": 0.5837511244377811
    },
    {
      "epoch": 7,
      "train_loss": 0.4599461654822032,
      "val_auc": 0.5672593703148425
    },
    {
      "epoch": 8,
      "train_loss": 0.4304879903793335,
      "val_auc": 0.5841739130434782
    },
    {
      "epoch": 9,
      "train_loss": 0.4048189151854742,
      "val_auc": 0.5825157421289355
    },
    {
      "epoch": 10,
      "train_loss": 0.3700132242270878,
      "val_auc": 0.5780119940029985
    },
    {
      "epoch": 11,
      "train_loss": 0.3446728913556962,
      "val_auc": 0.5552473763118442
    },
    {
      "epoch": 12,
      "train_loss": 0.3141884562515077,
      "val_auc": 0.5655502248875561
    },
    {
      "epoch": 13,
      "train_loss": 0.27776039640108746,
      "val_auc": 0.566431784107946
    }
  ],
  "best_val_auc": 0.5841739130434782,
  "best_epoch": 8,
  "epochs_ran": 13,
  "test_evaluated": false
}