{
  "setting": "none",
  "seed": 0,
  "config": {
    "id": "h128_lr3e4_d30_focal",
    "hidden": 128,
    "lr": 0.0003,
    "dropout": 0.3,
    "loss": "focal"
  },
  "history": [
    {
      "epoch": 1,
      "train_loss": 0.07483207611810594,
      "val_auc": 0.5243808095952024
    },
    {
      "epoch": 2,
      "train_loss": 0.06570208675804592,
      "val_auc": 0.5250524737631184
    },
    {
      "epoch": 3,
      "train_loss": 0.06390393241530373,
      "val_auc": 0.5265187406296852
    },
    {
      "epoch": 4,
      "train_loss": 0.061902452082861034,
      "val_auc": 0.5212743628185907
    },
    {
      "epoch": 5,
      "train_loss": 0.06134781188198498,
      "val_auc": 0.5381619190404798
    },
    {
      "epoch": 6,
      "train_loss": 0.05978589912965184,
      "val_auc": 0.5325307346326836
    },
    {
      "epoch": 7,
      "train_loss": 0.058601241204000655,
      "val_auc": 0.5409745127436283
    },
    {
      "epoch": 8,
      "train_loss": 0.05742939685781797,
      "val_auc": 0.5401169415292354
    },
    {
      "epoch": 9,
      "train_loss": 0.056676301395609266,
      "val_auc": 0.5311484257871065
    },
    {
      "epoch": 10,
      "train_loss": 0.05541420745707694,
      "val_auc": 0.5511694152923537
    },
    {
      "epoch": 11,
      "train_loss": 0.05431914027957689,
      "val_auc": 0.5488185907046477
    },
    {
      "epoch": 12,
      "train_loss": 0.05344350369913237,
      "val_auc": 0.5547316341829086
    },
    {
      "epoch": 13,
      "train_loss": 0.05208534960235868,
      "val_auc": 0.5413643178410794
    },
    {
      "epoch": 14,
      "train_loss": 0.05098065148506846,
      "val_auc": 0.5539040479760119
    },
    {
      "epoch": 15,
      "train_loss": 0.04996447903769357,
      "val_auc": 0.5529085457271365
    },
    {
      "epoch": 16,
      "train_loss": 0.04826528916046733,
      "val_auc": 0.5471934032983509
    },
    {
      "epoch": 17,
      "train_loss": 0.04705154949000904,
      "val_auc": 0.5533883058470764
    }
  ],
  "best_val_auc": 0.5547316341829086,
  "best_epoch": 12,
  "epochs_ran": 17,
  "test_evaluated": false
}