{
  "setting": "none",
  "seed": 2,
  "config": {
    "id": "h128_lr3e4_d30_focal",
    "hidden": 128,
    "lr": 0.0003,
    "dropout": 0.3,
    "loss": "focal"
  },
  "metrics": {
    "base_rate": 0.58068669527897,
    "weighted_f1": 0.4338917054221565,
    "macro_f1": 0.37612098433237734,
    "shift_f1": 0.7341150804472321,
    "noshift_f1": 0.01812688821752266,
    "shift_precision": 0.581676750216076,
    "shift_recall": 0.9948263118994827,
    "balanced_acc": 0.5020190924901712,
    "frac_pred_shift": 0.9931330472103004,
    "degenerate": true,
    "shift_auc": 0.6292979473946596,
    "shift_pr_auc": 0.6998374836543503,
    "brier": 0.23732837984127084,
    "ece10": 0.06160453527270464
  },
  "threshold": 0.5291260480880737,
  "history": [
    {
      "epoch": 1,
      "train_loss": 0.06906097246841951,
      "val_auc": 0.5730183936547836
    },
    {
      "epoch": 2,
      "train_loss": 0.06593626669862053,
      "val_auc": 0.5774405985155998
    },
    {
      "epoch": 3,
      "train_loss": 0.06534838394233675,
      "val_auc": 0.5773323256169433
    },
    {
      "epoch": 4,
      "train_loss": 0.06509943058093388,
      "val_auc": 0.5891319485724962
    },
    {
      "epoch": 5,
      "train_loss": 0.06419375448515921,
      "val_auc": 0.5927962431427165
    },
    {
      "epoch": 6,
      "train_loss": 0.06404844615044016,
      "val_auc": 0.591876985003142
    },
    {
      "epoch": 7,
      "train_loss": 0.06335567920045419,
      "val_auc": 0.5997978905891744
    },
    {
      "epoch": 8,
      "train_loss": 0.06253959735234578,
      "val_auc": 0.594789738276805
    },
    {
      "epoch": 9,
      "train_loss": 0.061909451742063866,
      "val_auc": 0.5907730260364477
    },
    {
      "epoch": 10,
      "train_loss": 0.06164255726969603,
      "val_auc": 0.5935817524074798
    },
    {
      "epoch": 11,
      "train_loss": 0.060119469621867844,
      "val_auc": 0.5923822585302061
    },
    {
      "epoch": 12,
      "train_loss": 0.0597137761386958,
      "val_auc": 0.5806378335229878
    }
  ],
  "best_val_auc": 0.5997978905891744,
  "best_epoch": 7,
  "epochs_ran": 12,
  "scores_file": "final_none_seed2.npz"
}